subrip_sync/__init__.py
subrip_sync/cli.py
subrip_sync/subrip.py
subrip_sync/test_srtsync.py
subrip_sync-0.1.2.dist-info/METADATA
subrip_sync-0.1.2.dist-info/WHEEL
subrip_sync-0.1.2.dist-info/entry_points.txt
subrip_sync-0.1.2.dist-info/RECORD
