Metadata-Version: 2.4
Name: subrip-sync
Version: 0.1.2
Summary: Sync SubRip subtitle with audio
Project-URL: Repository, https://github.com/maduma/subrip-sync
Author-email: maduma@pt.lu
Requires-Python: >=3.6
